pydactory/__init__.py
pydactory/errors.py
pydactory/fake.py
pydactory/gen.py
pydactory/params.py
pydactory/pydactory.py
pydactory/types.py
pydactory-0.2.0.dist-info/LICENSE.txt
pydactory-0.2.0.dist-info/WHEEL
pydactory-0.2.0.dist-info/METADATA
pydactory-0.2.0.dist-info/RECORD
