Metadata-Version: 2.1
Name: pydactory
Version: 0.2.0
Summary: A factory library for pydantic models.
Home-page: https://github.com/rthoward/pydactory
License: MIT
Keywords: factory,fixture,pydantic
Author: Richard Howard
Author-email: richard@howard.io
Requires-Python: >=3.8,<4.0
Classifier: License :: OSI Approved :: MIT License
Classifier: Programming Language :: Python :: 3
Classifier: Programming Language :: Python :: 3.8
Classifier: Programming Language :: Python :: 3.9
Requires-Dist: faker (>=4.15.0,<5.0.0)
Requires-Dist: pydantic (>=1.7.2,<2.0.0)
